peakrdl_rawheader/__init__.py
peakrdl_rawheader/__peakrdl__.py
peakrdl_rawheader/rawheader_fns.py
peakrdl_rawheader/templates/c.mako
peakrdl_rawheader/templates/svh.mako
peakrdl_rawheader/templates/svpkg.mako
peakrdl_rawheader/utils.py
peakrdl_rawheader-0.2.1.dist-info/WHEEL
peakrdl_rawheader-0.2.1.dist-info/entry_points.txt
peakrdl_rawheader-0.2.1.dist-info/METADATA
peakrdl_rawheader-0.2.1.dist-info/RECORD
