Metadata-Version: 2.3
Name: peakrdl-rawheader
Version: 0.2.1
Summary: Generate Header files from a SystemRDL register model
Keywords: SystemRDL,PeakRDL,CSR,compiler,tool,registers,generator,C,header,software,SystemVerilog
Author: Michael Rogenmoser
License:                                  Apache License
Classifier: Development Status :: 5 - Production/Stable
Classifier: Programming Language :: Python
Classifier: Programming Language :: Python :: 3
Classifier: Programming Language :: Python :: 3 :: Only
Classifier: Intended Audience :: Developers
Classifier: License :: OSI Approved :: Apache Software License
Classifier: Operating System :: OS Independent
Classifier: Topic :: Scientific/Engineering :: Electronic Design Automation (EDA)
Requires-Dist: mako>=1.2.4
Requires-Dist: systemrdl-compiler>=1.29.0,<2
Requires-Dist: peakrdl-cli>=1.2.3 ; extra == 'cli'
Requires-Dist: peakrdl ; extra == 'test'
Requires-Dist: pytest ; extra == 'test'
Requires-Python: >=3.10
Provides-Extra: cli
Provides-Extra: test
